dotvar/__init__.py
dotvar/auto_load.py
dotvar/auto_load_strict.py
dotvar/env_loader.py
dotvar-0.1.12.dist-info/METADATA
dotvar-0.1.12.dist-info/WHEEL
dotvar-0.1.12.dist-info/RECORD
